JavaServlet31Guifan/README.md
JavaServlet31Guifan/__init__.py
JavaServlet31Guifan/__main__.py
JavaServlet31Guifan/file.epub
JavaServlet31Guifan/index.html
JavaServlet31Guifan/css/__init__.py
JavaServlet31Guifan/css/annotations.css
JavaServlet31Guifan/css/main.css
JavaServlet31Guifan/css/normalize.css
JavaServlet31Guifan/css/popup.css
JavaServlet31Guifan/font/__init__.py
JavaServlet31Guifan/font/fontello.eot
JavaServlet31Guifan/font/fontello.svg
JavaServlet31Guifan/font/fontello.ttf
JavaServlet31Guifan/font/fontello.woff
JavaServlet31Guifan/img/__init__.py
JavaServlet31Guifan/img/annotator-glyph-sprite.png
JavaServlet31Guifan/img/annotator-icon-sprite.png
JavaServlet31Guifan/img/apple-touch-icon.png
JavaServlet31Guifan/img/cancelfullscreen.png
JavaServlet31Guifan/img/close.png
JavaServlet31Guifan/img/fullscreen.png
JavaServlet31Guifan/img/loader.gif
JavaServlet31Guifan/img/menu-icon.png
JavaServlet31Guifan/img/save.png
JavaServlet31Guifan/img/saved.png
JavaServlet31Guifan/img/settings-s.png
JavaServlet31Guifan/img/settings.png
JavaServlet31Guifan/img/star.png
JavaServlet31Guifan/js/__init__.py
JavaServlet31Guifan/js/epub.js
JavaServlet31Guifan/js/epub.min.js
JavaServlet31Guifan/js/epub.min.map
JavaServlet31Guifan/js/hooks.min.js
JavaServlet31Guifan/js/hooks.min.map
JavaServlet31Guifan/js/reader.js
JavaServlet31Guifan/js/reader.js.map
JavaServlet31Guifan/js/reader.min.js
JavaServlet31Guifan/js/reader.min.map
JavaServlet31Guifan/js/hooks/__init__.py
JavaServlet31Guifan/js/hooks/extensions/__init__.py
JavaServlet31Guifan/js/hooks/extensions/highlight.js
JavaServlet31Guifan/js/libs/__init__.py
JavaServlet31Guifan/js/libs/jquery.min.js
JavaServlet31Guifan/js/libs/localforage.min.js
JavaServlet31Guifan/js/libs/screenfull.js
JavaServlet31Guifan/js/libs/screenfull.min.js
JavaServlet31Guifan/js/libs/zip.min.js
JavaServlet31Guifan/js/plugins/__init__.py
JavaServlet31Guifan/js/plugins/hypothesis.js
JavaServlet31Guifan/js/plugins/search.js
java_servlet_3_1_guifan-2024.3.1.0.dist-info/METADATA
java_servlet_3_1_guifan-2024.3.1.0.dist-info/WHEEL
java_servlet_3_1_guifan-2024.3.1.0.dist-info/entry_points.txt
java_servlet_3_1_guifan-2024.3.1.0.dist-info/top_level.txt
java_servlet_3_1_guifan-2024.3.1.0.dist-info/RECORD
